[{"__type__":"cc.SpriteFrame","content":{"name":"tang","texture":"2aZ5qGeGlDcISZTBYaIDM9","rect":[0,0,63,63],"offset":[-0.5,0],"originalSize":[64,63]}},[{"__type__":"cc.Prefab","_name":"fxSkillBullet","data":{"__id__":1},"asyncLoadAssets":null},{"__type__":"cc.Node","_name":"fxSkillBullet","_children":[{"__id__":2},{"__id__":4}],"_active":false,"_components":[{"__type__":"cc.Sprite","node":{"__id__":1},"_spriteFrame":{"__uuid__":"35Dmq6XyhISbgnzIT5dyEb"},"_sizeMode":0},{"__id__":5},{"__type__":"0c656atI3BPwJrhEzYDcD7/","node":{"__id__":1},"listAnimation":[{"__id__":5}],"listParticleSystem":[{"__id__":3}]}],"_prefab":{"__type__":"cc.PrefabInfo","root":{"__id__":1},"asset":{"__uuid__":"4eaSFoJY1E6brvxWhaC7qX"},"fileId":"d6j2hK4/FJ/YbDf0+wIRhZ"},"_contentSize":{"__type__":"cc.Size","width":250,"height":250},"_scaleX":0.5,"_scaleY":0.5,"_position":{"__type__":"cc.Vec2","x":5,"y":212}},{"__type__":"cc.Node","_name":"shouji_lizi","_parent":{"__id__":1},"_components":[{"__id__":3}],"_prefab":{"__type__":"cc.PrefabInfo","root":{"__id__":1},"asset":{"__uuid__":"4eaSFoJY1E6brvxWhaC7qX"},"fileId":"77bmXsghhM25xg8KcATLRS"}},{"__type__":"cc.ParticleSystem","node":{"__id__":2},"_custom":true,"_texture":{"__uuid__":"34BVgoLbVJaourCpMdasMQ"},"_srcBlendFactor":1,"_dstBlendFactor":1,"_totalParticles":12,"_duration":1,"_emissionRate":30,"_life":0.6,"_lifeVar":0.2,"_startColor":{"__type__":"cc.Color","r":255,"g":255,"b":255,"a":240},"_startColorVar":{"__type__":"cc.Color","r":79,"g":112,"b":138,"a":0},"_endColor":{"__type__":"cc.Color","r":255,"g":255,"b":255},"_endColorVar":{"__type__":"cc.Color","r":46,"g":46,"b":46,"a":46},"_angle":0,"_angleVar":360,"_startSize":200,"_startSizeVar":60,"_endSizeVar":7,"_startSpinVar":180,"_endSpinVar":180,"_posVar":{"__type__":"cc.Vec2","x":12,"y":12},"_emitterMode":1,"_gravity":{"__type__":"cc.Vec2","y":-300},"_speed":500,"_speedVar":400,"_tangentialAccel":0,"_startRadius":20,"_endRadius":170,"_endRadiusVar":60},{"__type__":"cc.Node","_name":"4-2","_parent":{"__id__":1},"_components":[{"__type__":"cc.Sprite","node":{"__id__":4},"_spriteFrame":{"__uuid__":"b0oc4quptKPIUzthk8g1FH"},"_sizeMode":0}],"_prefab":{"__type__":"cc.PrefabInfo","root":{"__id__":1},"asset":{"__uuid__":"4eaSFoJY1E6brvxWhaC7qX"},"fileId":"3d+D783xhLEKmnWwoziBVs"},"_contentSize":{"__type__":"cc.Size","width":230,"height":230},"_scaleX":2,"_scaleY":2},{"__type__":"cc.Animation","node":{"__id__":1},"_defaultClip":{"__uuid__":"90UcpymOBDnZ0I7BK5D4pw"},"_clips":[{"__uuid__":"90UcpymOBDnZ0I7BK5D4pw"}]}],{"__type__":"cc.SpriteFrame","content":{"name":"4-2","texture":"89/ZvajkRFgZJ8cETpCXMY","rect":[3,0,253,250],"offset":[1.5,3],"originalSize":[256,256]}}]