[{"__type__":"cc.SpriteFrame","content":{"name":"mum","texture":"1d18970d0","rect":[819,822,74,183],"offset":[0,0],"originalSize":[74,183],"rotated":1,"capInsets":[0,0,0,0]}},[{"__type__":"cc.Prefab","_name":"Level_34","data":{"__id__":1}},{"__type__":"cc.Node","_name":"Level_34","_children":[{"__id__":2},{"__id__":3},{"__id__":4},{"__id__":5},{"__id__":6},{"__id__":7},{"__id__":8},{"__id__":9}],"_level":6,"_components":[{"__type__":"cc.Widget","node":{"__id__":1},"_alignFlags":45},{"__type__":"87531oDQTNNSak/UliEnXnA","node":{"__id__":1},"tips":"口罩，妈妈女朋友都要带，想个办法变出两个吧！","listBtn":[{"__id__":3},{"__id__":4}],"btnC":{"__id__":9},"maskCopy":{"__id__":8},"mask":{"__id__":7},"nodeWifeFace":{"__id__":5},"nodeMumFace":{"__id__":6}}],"_prefab":{"__type__":"cc.PrefabInfo","root":{"__id__":1},"asset":{"__uuid__":"9dYzfP9jJJkrgakuTVNqjr"},"fileId":"1deXMAX6hCWog/2Hh9QcUG"},"_contentSize":{"__type__":"cc.Size","width":635,"height":745}},{"__type__":"cc.Node","_name":"Title","_parent":{"__id__":1},"_level":7,"_components":[{"__type__":"cc.Label","node":{"__id__":2},"_materials":[{"__uuid__":"ecpdLyjvZBwrvm+cedCcQy"}],"_useOriginalSize":false,"_string":"口罩，是给妈妈，还是给女朋友？","_N$string":"口罩，是给妈妈，还是给女朋友？","_fontSize":45,"_lineHeight":45,"_N$file":{"__uuid__":"7ebQYRObFNMrGttAPpBzE4"},"_isSystemFontUsed":false,"_N$overflow":1},{"__type__":"cc.Widget","node":{"__id__":2},"_alignFlags":41,"_left":20,"_right":20,"_top":20,"_originalWidth":89.28}],"_prefab":{"__type__":"cc.PrefabInfo","root":{"__id__":1},"asset":{"__uuid__":"9dYzfP9jJJkrgakuTVNqjr"},"fileId":"a50nGVgYVHj75jUcuRXqjm"},"_color":{"__type__":"cc.Color"},"_contentSize":{"__type__":"cc.Size","width":595,"height":200},"_position":{"__type__":"cc.Vec3","y":252.5}},{"__type__":"cc.Node","_name":"mum","_parent":{"__id__":1},"_level":7,"_components":[{"__type__":"cc.Sprite","node":{"__id__":3},"_materials":[{"__uuid__":"ecpdLyjvZBwrvm+cedCcQy"}],"_spriteFrame":{"__uuid__":"50xWyNP4ROZJ6Vdp3psoek"}}],"_prefab":{"__type__":"cc.PrefabInfo","root":{"__id__":1},"asset":{"__uuid__":"9dYzfP9jJJkrgakuTVNqjr"},"fileId":"76qv4SnjVKMbqKvl+3Ljvl"},"_contentSize":{"__type__":"cc.Size","width":74,"height":183},"_position":{"__type__":"cc.Vec3","x":128.362,"y":-32.09},"_scale":{"__type__":"cc.Vec3","x":1.5,"y":1.5,"z":1}},{"__type__":"cc.Node","_name":"wife","_parent":{"__id__":1},"_level":7,"_components":[{"__type__":"cc.Sprite","node":{"__id__":4},"_materials":[{"__uuid__":"ecpdLyjvZBwrvm+cedCcQy"}],"_spriteFrame":{"__uuid__":"b28U2J/+xP/6PIvbv/CT0c"}}],"_prefab":{"__type__":"cc.PrefabInfo","root":{"__id__":1},"asset":{"__uuid__":"9dYzfP9jJJkrgakuTVNqjr"},"fileId":"e7xbdNFXtE55bnmiF04SV8"},"_contentSize":{"__type__":"cc.Size","width":98,"height":182},"_position":{"__type__":"cc.Vec3","x":-107.503,"y":-32.09},"_scale":{"__type__":"cc.Vec3","x":1.5,"y":1.5,"z":1}},{"__type__":"cc.Node","_name":"wifeFace","_parent":{"__id__":1},"_level":7,"_prefab":{"__type__":"cc.PrefabInfo","root":{"__id__":1},"asset":{"__uuid__":"9dYzfP9jJJkrgakuTVNqjr"},"fileId":"06/hClmhJGFKmfNaWTf06n"},"_contentSize":{"__type__":"cc.Size","width":100,"height":50},"_position":{"__type__":"cc.Vec3","x":-107.503,"y":30.993}},{"__type__":"cc.Node","_name":"mumFace","_parent":{"__id__":1},"_level":7,"_prefab":{"__type__":"cc.PrefabInfo","root":{"__id__":1},"asset":{"__uuid__":"9dYzfP9jJJkrgakuTVNqjr"},"fileId":"07Vm6XTyRB6pcebTAVtAnM"},"_contentSize":{"__type__":"cc.Size","width":100,"height":50},"_position":{"__type__":"cc.Vec3","x":129.363,"y":30.993}},{"__type__":"cc.Node","_name":"Mask","_parent":{"__id__":1},"_level":7,"_components":[{"__type__":"cc.Sprite","node":{"__id__":7},"_materials":[{"__uuid__":"ecpdLyjvZBwrvm+cedCcQy"}],"_spriteFrame":{"__uuid__":"a3+vf8hFNPQqRAwo94o4zU"}},{"__type__":"9fdc4nMl4VGS7z7NqYVo2lo","node":{"__id__":7}}],"_prefab":{"__type__":"cc.PrefabInfo","root":{"__id__":1},"asset":{"__uuid__":"9dYzfP9jJJkrgakuTVNqjr"},"fileId":"b6WfLBZ6ZMhY+aI0d3uu6z"},"_contentSize":{"__type__":"cc.Size","width":57,"height":34},"_position":{"__type__":"cc.Vec3","x":-115.559,"y":222.57600000000002},"_scale":{"__type__":"cc.Vec3","x":1.5,"y":1.5,"z":1.5}},{"__type__":"cc.Node","_name":"Mask","_parent":{"__id__":1},"_active":false,"_level":7,"_components":[{"__type__":"cc.Sprite","node":{"__id__":8},"_materials":[{"__uuid__":"ecpdLyjvZBwrvm+cedCcQy"}],"_spriteFrame":{"__uuid__":"a3+vf8hFNPQqRAwo94o4zU"}},{"__type__":"9fdc4nMl4VGS7z7NqYVo2lo","node":{"__id__":8}}],"_prefab":{"__type__":"cc.PrefabInfo","root":{"__id__":1},"asset":{"__uuid__":"9dYzfP9jJJkrgakuTVNqjr"},"fileId":"2afgmTo8hDYpmmq2ueBYcg"},"_contentSize":{"__type__":"cc.Size","width":57,"height":34},"_position":{"__type__":"cc.Vec3","x":109.142,"y":219.36699999999996},"_scale":{"__type__":"cc.Vec3","x":1.5,"y":1.5,"z":1.5}},{"__type__":"cc.Node","_name":"BtnC","_parent":{"__id__":1},"_children":[{"__id__":10}],"_active":false,"_level":7,"_components":[{"__type__":"cc.Sprite","node":{"__id__":9},"_materials":[{"__uuid__":"ecpdLyjvZBwrvm+cedCcQy"}],"_spriteFrame":{"__uuid__":"e7e4WNKbdGnpUPjKf7Angv"},"_type":1,"_sizeMode":0}],"_prefab":{"__type__":"cc.PrefabInfo","root":{"__id__":1},"asset":{"__uuid__":"9dYzfP9jJJkrgakuTVNqjr"},"fileId":"0d1t/VgvtMuovd3DiQ2HFH"},"_color":{"__type__":"cc.Color","r":150,"g":235,"b":255},"_contentSize":{"__type__":"cc.Size","width":90,"height":80},"_position":{"__type__":"cc.Vec3","x":-112.316,"y":143.66100000000006}},{"__type__":"cc.Node","_name":"Label","_parent":{"__id__":9},"_level":8,"_components":[{"__type__":"cc.Label","node":{"__id__":10},"_materials":[{"__uuid__":"ecpdLyjvZBwrvm+cedCcQy"}],"_useOriginalSize":false,"_string":"复制","_N$string":"复制","_fontSize":45,"_lineHeight":45,"_N$file":{"__uuid__":"7ebQYRObFNMrGttAPpBzE4"},"_isSystemFontUsed":false,"_N$horizontalAlign":1,"_N$verticalAlign":1}],"_prefab":{"__type__":"cc.PrefabInfo","root":{"__id__":1},"asset":{"__uuid__":"9dYzfP9jJJkrgakuTVNqjr"},"fileId":"41uIlQW7NESb8GXohFFJXK"},"_color":{"__type__":"cc.Color"},"_contentSize":{"__type__":"cc.Size","width":90,"height":56.7},"_position":{"__type__":"cc.Vec3","y":5}}],{"__type__":"cc.SpriteFrame","content":{"name":"mask","texture":"1d18970d0","rect":[164,1312,57,34],"offset":[0,0],"originalSize":[57,34],"capInsets":[0,0,0,0]}},{"__type__":"cc.SpriteFrame","content":{"name":"wife","texture":"1d18970d0","rect":[237,979,98,182],"offset":[0,0],"originalSize":[98,182],"rotated":1,"capInsets":[0,0,0,0]}},{"__type__":"cc.SpriteFrame","content":{"name":"btn_common","texture":"12d21477e","rect":[695,843,58,59],"offset":[0,0],"originalSize":[58,59],"rotated":1,"capInsets":[29,29,29,30]}}]