[{"__type__":"cc.SpriteFrame","content":{"name":"sprDoubleAds","texture":"2cA7HUk3ZN7o0oqP+oVzAF","rect":[1584,1300,93,81],"offset":[0,0],"originalSize":[93,81],"rotated":1}},{"__type__":"cc.SpriteFrame","content":{"name":"btnCommon3","texture":"2cA7HUk3ZN7o0oqP+oVzAF","rect":[1670,1212,312,104],"offset":[0,0],"originalSize":[312,104]}},{"__type__":"cc.SpriteFrame","content":{"name":"default_btn_disabled","texture":"71VhFCTINJM6/Ky3oX9nBT","rect":[0,0,40,40],"offset":[0,0],"originalSize":[40,40],"capInsets":[15,7,15,9]}},{"__type__":"cc.SpriteFrame","content":{"name":"advJump","texture":"2cA7HUk3ZN7o0oqP+oVzAF","rect":[305,542,253,45],"offset":[0,0],"originalSize":[253,45]}},[{"__type__":"cc.Prefab","_name":"UIAdvPanel","data":{"__id__":1},"asyncLoadAssets":null},{"__type__":"cc.Node","_name":"UIAdvPanel","_children":[{"__id__":2},{"__id__":3},{"__id__":8},{"__id__":16}],"_components":[{"__type__":"965241VW8ZLdZ1kXO8fO0Jp","node":{"__id__":1},"Widget":{"__id__":1},"nodeAdvPanel":{"__id__":3},"nodeGoldPanel":{"__id__":8},"btnView":{"__id__":7},"btnPass":{"__id__":17},"btnGoldRevive":{"__id__":17},"labRemainGold":{"__id__":15}}],"_prefab":{"__type__":"cc.PrefabInfo","root":{"__id__":1},"asset":{"__uuid__":"70ro5mIZdGE5LeY7P8IpQc"},"fileId":"01ZPFR7C9MLYCtHT4N8w0N"}},{"__type__":"cc.Node","_name":"bg","_parent":{"__id__":1},"_components":[{"__type__":"cc.Sprite","node":{"__id__":2},"_spriteFrame":{"__uuid__":"eaOcEhHsVCI7SI0qwT744C"},"_sizeMode":0},{"__type__":"f6635CCbQhD7IG/pOXxxEyM","node":{"__id__":2}}],"_prefab":{"__type__":"cc.PrefabInfo","root":{"__id__":1},"asset":{"__uuid__":"70ro5mIZdGE5LeY7P8IpQc"},"fileId":"cdNn74sxNEk4rTkz6f+AHe"},"_opacity":180,"_color":{"__type__":"cc.Color"},"_contentSize":{"__type__":"cc.Size","width":750,"height":1334}},{"__type__":"cc.Node","_name":"advPanel","_parent":{"__id__":1},"_children":[{"__id__":4}],"_prefab":{"__type__":"cc.PrefabInfo","root":{"__id__":1},"asset":{"__uuid__":"70ro5mIZdGE5LeY7P8IpQc"},"fileId":"fetYAA9MJLCbf3p5koYrV5"}},{"__type__":"cc.Node","_name":"btnReview","_parent":{"__id__":3},"_children":[{"__id__":5},{"__id__":6}],"_components":[{"__type__":"cc.Sprite","node":{"__id__":4},"_spriteFrame":{"__uuid__":"29Dba/iXxCrIRMOB5PHjnT"},"_type":1,"_sizeMode":0},{"__id__":7}],"_prefab":{"__type__":"cc.PrefabInfo","root":{"__id__":1},"asset":{"__uuid__":"70ro5mIZdGE5LeY7P8IpQc"},"fileId":"20rtRbn5FMiq7DNbxAoft9"},"_contentSize":{"__type__":"cc.Size","width":380,"height":130},"_position":{"__type__":"cc.Vec2","y":-93.2}},{"__type__":"cc.Node","_name":"btnReview","_parent":{"__id__":4},"_components":[{"__type__":"cc.Sprite","node":{"__id__":5},"_spriteFrame":{"__uuid__":"7efM0zqSJJyJvtihDNnBN7"}}],"_prefab":{"__type__":"cc.PrefabInfo","root":{"__id__":1},"asset":{"__uuid__":"70ro5mIZdGE5LeY7P8IpQc"},"fileId":"34qGi4EXRJoZNQKvdnsEuF"},"_contentSize":{"__type__":"cc.Size","width":149,"height":69},"_position":{"__type__":"cc.Vec2","x":54.7}},{"__type__":"cc.Node","_name":"btnReview2","_parent":{"__id__":4},"_components":[{"__type__":"cc.Sprite","node":{"__id__":6},"_spriteFrame":{"__uuid__":"12JFH39ZZAl698IR4u4lih"}}],"_prefab":{"__type__":"cc.PrefabInfo","root":{"__id__":1},"asset":{"__uuid__":"70ro5mIZdGE5LeY7P8IpQc"},"fileId":"f59L0LTKNMwaCYjZTROkB0"},"_contentSize":{"__type__":"cc.Size","width":93,"height":81},"_position":{"__type__":"cc.Vec2","x":-80.7}},{"__type__":"cc.Button","node":{"__id__":4},"transition":3,"pressedColor":{"__type__":"cc.Color","r":103,"g":121,"b":195},"zoomScale":0.9,"clickEvents":[{"__type__":"cc.ClickEvent","target":{"__id__":1},"component":"UIAdvPanel","handler":"onClickView"}],"_N$enableAutoGrayEffect":true,"_N$normalColor":{"__type__":"cc.Color","r":255,"g":255,"b":255},"_N$disabledColor":{"__type__":"cc.Color","r":255,"g":255,"b":255},"_N$pressedSprite":{"__uuid__":"e97GVMl6JHh5Ml5qEDdSGa"},"pressedSprite":{"__uuid__":"e97GVMl6JHh5Ml5qEDdSGa"},"_N$hoverSprite":{"__uuid__":"e97GVMl6JHh5Ml5qEDdSGa"},"hoverSprite":{"__uuid__":"e97GVMl6JHh5Ml5qEDdSGa"},"_N$disabledSprite":{"__uuid__":"29FYIk+N1GYaeWH/q1NxQO"},"_N$target":{"__id__":4}},{"__type__":"cc.Node","_name":"goldPanel","_parent":{"__id__":1},"_children":[{"__id__":9},{"__id__":13},{"__id__":14}],"_active":false,"_prefab":{"__type__":"cc.PrefabInfo","root":{"__id__":1},"asset":{"__uuid__":"70ro5mIZdGE5LeY7P8IpQc"},"fileId":"10ApcZAt9KN4eLXUWxI2zw"}},{"__type__":"cc.Node","_name":"btnRevive","_parent":{"__id__":8},"_children":[{"__id__":10},{"__id__":11},{"__id__":12}],"_components":[{"__type__":"cc.Sprite","node":{"__id__":9},"_spriteFrame":{"__uuid__":"29Dba/iXxCrIRMOB5PHjnT"},"_type":1,"_sizeMode":0},{"__type__":"cc.Button","node":{"__id__":9},"transition":3,"pressedColor":{"__type__":"cc.Color","r":103,"g":121,"b":195},"zoomScale":0.9,"clickEvents":[{"__type__":"cc.ClickEvent","target":{"__id__":1},"component":"UIAdvPanel","handler":"onClickGoldRevive"}],"_N$normalColor":{"__type__":"cc.Color","r":255,"g":255,"b":255},"_N$disabledColor":{"__type__":"cc.Color","r":255,"g":255,"b":255},"_N$pressedSprite":{"__uuid__":"e97GVMl6JHh5Ml5qEDdSGa"},"pressedSprite":{"__uuid__":"e97GVMl6JHh5Ml5qEDdSGa"},"_N$hoverSprite":{"__uuid__":"e97GVMl6JHh5Ml5qEDdSGa"},"hoverSprite":{"__uuid__":"e97GVMl6JHh5Ml5qEDdSGa"},"_N$disabledSprite":{"__uuid__":"29FYIk+N1GYaeWH/q1NxQO"},"_N$target":{"__id__":9}}],"_prefab":{"__type__":"cc.PrefabInfo","root":{"__id__":1},"asset":{"__uuid__":"70ro5mIZdGE5LeY7P8IpQc"},"fileId":"47mQQ/EcBDz6se76R8m7sX"},"_contentSize":{"__type__":"cc.Size","width":310,"height":100},"_position":{"__type__":"cc.Vec2","y":56}},{"__type__":"cc.Node","_name":"btnReview","_parent":{"__id__":9},"_components":[{"__type__":"cc.Sprite","node":{"__id__":10},"_spriteFrame":{"__uuid__":"7efM0zqSJJyJvtihDNnBN7"}}],"_prefab":{"__type__":"cc.PrefabInfo","root":{"__id__":1},"asset":{"__uuid__":"70ro5mIZdGE5LeY7P8IpQc"},"fileId":"ceacqOH+9LNpu6HZMaT3/h"},"_contentSize":{"__type__":"cc.Size","width":149,"height":69},"_scaleX":0.6,"_scaleY":0.6,"_position":{"__type__":"cc.Vec2","x":66.3}},{"__type__":"cc.Node","_name":"gold","_parent":{"__id__":9},"_components":[{"__type__":"cc.Sprite","node":{"__id__":11},"_spriteFrame":{"__uuid__":"ceVWqoqc9I6bIrFaxlh3tH"}}],"_prefab":{"__type__":"cc.PrefabInfo","root":{"__id__":1},"asset":{"__uuid__":"70ro5mIZdGE5LeY7P8IpQc"},"fileId":"32gNjTfhJGaYBeuyLgjasz"},"_contentSize":{"__type__":"cc.Size","width":86,"height":87},"_scaleX":0.6,"_scaleY":0.6,"_position":{"__type__":"cc.Vec2","x":-10,"y":-1}},{"__type__":"cc.Node","_name":"New Label","_parent":{"__id__":9},"_components":[{"__type__":"cc.Label","node":{"__id__":12},"_useOriginalSize":false,"_N$file":{"__uuid__":"f71ulXGsVLiJF961RSSiG0"},"_isSystemFontUsed":false,"_N$string":"1000","_N$horizontalAlign":1,"_N$verticalAlign":1}],"_prefab":{"__type__":"cc.PrefabInfo","root":{"__id__":1},"asset":{"__uuid__":"70ro5mIZdGE5LeY7P8IpQc"},"fileId":"6ctEhBrupDVY9rVrg4gc8L"},"_contentSize":{"__type__":"cc.Size","width":88,"height":40},"_position":{"__type__":"cc.Vec2","x":-91.1,"y":-7.9}},{"__type__":"cc.Node","_name":"sprRemain","_parent":{"__id__":8},"_components":[{"__type__":"cc.Sprite","node":{"__id__":13},"_spriteFrame":{"__uuid__":"c3t+UsdQhNbbg66zWrV330"}}],"_prefab":{"__type__":"cc.PrefabInfo","root":{"__id__":1},"asset":{"__uuid__":"70ro5mIZdGE5LeY7P8IpQc"},"fileId":"c7cQny3sVHxajJsbc/qu7p"},"_contentSize":{"__type__":"cc.Size","width":297,"height":44},"_position":{"__type__":"cc.Vec2","x":-8.7,"y":-25.4}},{"__type__":"cc.Node","_name":"labRemain","_parent":{"__id__":8},"_components":[{"__id__":15}],"_prefab":{"__type__":"cc.PrefabInfo","root":{"__id__":1},"asset":{"__uuid__":"70ro5mIZdGE5LeY7P8IpQc"},"fileId":"1dXHqZ8TBIHZB6EX1NBXNi"},"_contentSize":{"__type__":"cc.Size","width":58.5,"height":15},"_position":{"__type__":"cc.Vec2","x":-5.1,"y":-20.6}},{"__type__":"cc.Label","node":{"__id__":14},"_useOriginalSize":false,"_actualFontSize":15,"_fontSize":15,"_N$file":{"__uuid__":"e4sJmeb+hB9b1sI8OcoHbL"},"_isSystemFontUsed":false,"_N$string":"999","_N$horizontalAlign":1,"_N$verticalAlign":1},{"__type__":"cc.Node","_name":"btnJump","_parent":{"__id__":1},"_components":[{"__type__":"cc.Sprite","node":{"__id__":16},"_spriteFrame":{"__uuid__":"60SNBHmRFBdLd+uCWEuSBU"},"_sizeMode":0},{"__id__":17}],"_prefab":{"__type__":"cc.PrefabInfo","root":{"__id__":1},"asset":{"__uuid__":"70ro5mIZdGE5LeY7P8IpQc"},"fileId":"97r/BMcdJK9Lc9syVOkg2T"},"_contentSize":{"__type__":"cc.Size","width":149,"height":31},"_scaleX":1.5,"_scaleY":1.5,"_position":{"__type__":"cc.Vec2","y":-252}},{"__type__":"cc.Button","node":{"__id__":16},"transition":3,"pressedColor":{"__type__":"cc.Color","r":103,"g":121,"b":195},"zoomScale":0.9,"clickEvents":[{"__type__":"cc.ClickEvent","target":{"__id__":1},"component":"UIAdvPanel","handler":"onClickPass"}],"_N$normalColor":{"__type__":"cc.Color","r":255,"g":255,"b":255},"_N$disabledColor":{"__type__":"cc.Color","r":255,"g":255,"b":255},"_N$pressedSprite":{"__uuid__":"e97GVMl6JHh5Ml5qEDdSGa"},"pressedSprite":{"__uuid__":"e97GVMl6JHh5Ml5qEDdSGa"},"_N$hoverSprite":{"__uuid__":"e97GVMl6JHh5Ml5qEDdSGa"},"hoverSprite":{"__uuid__":"e97GVMl6JHh5Ml5qEDdSGa"},"_N$disabledSprite":{"__uuid__":"29FYIk+N1GYaeWH/q1NxQO"},"_N$target":{"__id__":16}}],{"__type__":"cc.SpriteFrame","content":{"name":"advCountTips","texture":"2cA7HUk3ZN7o0oqP+oVzAF","rect":[2,1568,149,69],"offset":[0,0],"originalSize":[149,69]}},{"__type__":"cc.SpriteFrame","content":{"name":"gameOverDaily3","texture":"2cA7HUk3ZN7o0oqP+oVzAF","rect":[1539,716,297,44],"offset":[0,0],"originalSize":[297,44],"rotated":1}},{"__type__":"cc.SpriteFrame","content":{"name":"orange","texture":"92x1nBsZ1HqLs/vD3+O9ng","rect":[0,0,86,87],"offset":[0,0],"originalSize":[86,87]}},{"__type__":"cc.SpriteFrame","content":{"name":"default_btn_pressed","texture":"b4P/PCArtIdIH38t6mlw8Y","rect":[0,0,40,40],"offset":[0,0],"originalSize":[40,40],"capInsets":[11,11,11,7]}},{"__type__":"cc.SpriteFrame","content":{"name":"bg","texture":"08pAPsQRNC362YHkWkhzVs","rect":[0,0,750,1334],"offset":[0,0],"originalSize":[750,1334]}}]