[{"__type__":"cc.SpriteFrame","content":{"name":"Texture_014","texture":"153dfce38","rect":[233,889,80,26],"offset":[0,0],"originalSize":[80,26],"capInsets":[0,0,0,0]}},{"__type__":"cc.SpriteFrame","content":{"name":"Texture_023","texture":"153dfce38","rect":[316,975,41,41],"offset":[0.5,-0.5],"originalSize":[42,42],"capInsets":[0,0,0,0]}},[{"__type__":"cc.Prefab","_name":"Effect_Upgrade","data":{"__id__":1}},{"__type__":"cc.Node","_name":"Effect_Upgrade","_children":[{"__id__":2},{"__id__":4}],"_level":1,"_components":[{"__type__":"f0e78iDK+xFaq0BF1N0b1Jh","node":{"__id__":1},"listAnimation":[{"__id__":3}],"listParticleSystem":[{"__id__":5}]}],"_prefab":{"__type__":"cc.PrefabInfo","root":{"__id__":1},"asset":{"__uuid__":"faZvYec1VBB5ysWie3z4n2"},"fileId":"35qZM2slZBlof4gGodkZpp"},"_opacity":128},{"__type__":"cc.Node","_name":"Texture_014","_parent":{"__id__":1},"_level":2,"_components":[{"__type__":"cc.Sprite","node":{"__id__":2},"_spriteFrame":{"__uuid__":"59hV5yPp1Iaq7wIrnJsBQw"}},{"__id__":3}],"_prefab":{"__type__":"cc.PrefabInfo","root":{"__id__":1},"asset":{"__uuid__":"faZvYec1VBB5ysWie3z4n2"},"fileId":"d4mYLNevdLY5Bx5UNSnjxx"},"_opacity":0,"_contentSize":{"__type__":"cc.Size","width":80,"height":26},"_scale":{"__type__":"cc.Vec3","x":3.68,"y":3.68,"z":1}},{"__type__":"cc.Animation","node":{"__id__":2},"_defaultClip":{"__uuid__":"bfqZDhoW9OfrAsFr8FNobG"},"_clips":[{"__uuid__":"bfqZDhoW9OfrAsFr8FNobG"}]},{"__type__":"cc.Node","_name":"Mon","_parent":{"__id__":1},"_level":2,"_components":[{"__id__":5}],"_prefab":{"__type__":"cc.PrefabInfo","root":{"__id__":1},"asset":{"__uuid__":"faZvYec1VBB5ysWie3z4n2"},"fileId":"3eez7pZdtMq6p/9PYW82//"},"_position":{"__type__":"cc.Vec3","x":5,"y":4}},{"__type__":"cc.ParticleSystem","node":{"__id__":4},"_custom":true,"_spriteFrame":{"__uuid__":"63V/zyheBOwo6OZkKdKfa/"},"totalParticles":200,"duration":0.1,"emissionRate":200,"life":0.5,"lifeVar":0.25,"_startColor":{"__type__":"cc.Color","r":255,"g":255,"b":255},"_startColorVar":{"__type__":"cc.Color"},"_endColor":{"__type__":"cc.Color","r":255,"g":255,"b":255},"_endColorVar":{"__type__":"cc.Color"},"angleVar":0,"startSizeVar":30,"endSize":50,"posVar":{"__type__":"cc.Vec2","x":130,"y":30},"positionType":2,"gravity":{"__type__":"cc.Vec2","y":-3000},"speed":500,"speedVar":500,"tangentialAccel":0,"radialAccel":500,"radialAccelVar":500}]]