[{"__type__":"cc.AnimationClip","_name":"cubeDrop","_duration":0.43333333333333335,"sample":30,"curveData":{"paths":{"cube_face_0_Group":{"props":{"scaleX":[{"frame":0,"value":1}],"scaleY":[{"frame":0,"value":1}],"opacity":[{"frame":0,"value":0}]}},"cube_Group":{"props":{"scaleX":[{"frame":0,"value":1},{"frame":0.1,"value":1.12},{"frame":0.2,"value":0.9},{"frame":0.3,"value":1.06},{"frame":0.4,"value":1},{"frame":0.43333333333333335,"value":1}],"scaleY":[{"frame":0,"value":1},{"frame":0.13333333333333333,"value":0.69},{"frame":0.23333333333333334,"value":1.05},{"frame":0.3333333333333333,"value":0.89},{"frame":0.43333333333333335,"value":1}]}}}}},{"__type__":"cc.AnimationClip","_name":"cubeIdle","curveData":{"paths":{"cube_face_0_Group":{"props":{"scaleX":[{"frame":0,"value":1}],"scaleY":[{"frame":0,"value":1}],"opacity":[{"frame":0,"value":0}]}},"cube_Group":{"props":{"scaleX":[{"frame":0,"value":1}],"scaleY":[{"frame":0,"value":1}],"opacity":[{"frame":0,"value":255}]}},"cube_face_0_Group/cube_face_0":{"props":{"active":[{"frame":0,"value":true}]}},"face_0":{"props":{"active":[]}}}}},{"__type__":"cc.AnimationClip","_name":"cubeFace","_duration":0.3,"sample":30,"curveData":{"paths":{"cube_face_0_Group":{"props":{"scaleX":[{"frame":0.06666666666666667,"value":1.09},{"frame":0.16666666666666666,"value":0.97},{"frame":0.26666666666666666,"value":1}],"scaleY":[{"frame":0.06666666666666667,"value":0.89},{"frame":0.2,"value":1.08},{"frame":0.3,"value":1}],"opacity":[{"frame":0,"value":0},{"frame":0.13333333333333333,"value":0},{"frame":0.16666666666666666,"value":255},{"frame":0.3,"value":255}]}},"cube_Group":{"props":{"scaleX":[{"frame":0,"value":1},{"frame":0.06666666666666667,"value":1.09},{"frame":0.16666666666666666,"value":0.97},{"frame":0.26666666666666666,"value":1}],"scaleY":[{"frame":0,"value":1},{"frame":0.1,"value":0.89},{"frame":0.2,"value":1.08},{"frame":0.3,"value":1}],"opacity":[{"frame":0,"value":255},{"frame":0.13333333333333333,"value":255},{"frame":0.16666666666666666,"value":0},{"frame":0.3,"value":0}]}}}}},[{"__type__":"cc.Prefab","_name":"Cube","data":{"__id__":1},"asyncLoadAssets":true},{"__type__":"cc.Node","_name":"Cube","_children":[{"__id__":2},{"__id__":4},{"__id__":7},{"__id__":10}],"_level":1,"_components":[{"__type__":"1e62d7QYORE3ZlSmIic/8w1","node":{"__id__":1},"spriteCube":{"__id__":9},"spriteCubeFace":{"__id__":3},"spriteCubeFaceAnim":{"__id__":6},"animSelect":{"__id__":12},"spriteWater":{"__id__":11}},{"__id__":12}],"_prefab":{"__type__":"cc.PrefabInfo","root":{"__id__":1},"asset":{"__uuid__":"aa/BY2+fNF8o4wSArTqmho"},"fileId":"ec459/eN9PB6tVTybDGLmt"},"_contentSize":{"__type__":"cc.Size","width":90,"height":78},"_position":{"__type__":"cc.Vec3","x":45,"y":135},"_scale":{"__type__":"cc.Vec3","x":1,"y":1,"z":1}},{"__type__":"cc.Node","_name":"face_0","_parent":{"__id__":1},"_active":false,"_components":[{"__id__":3}],"_prefab":{"__type__":"cc.PrefabInfo","root":{"__id__":1},"asset":{"__uuid__":"aa/BY2+fNF8o4wSArTqmho"},"fileId":"0115U0cTZBsLYCjYc7dmWH"},"_contentSize":{"__type__":"cc.Size","width":86,"height":73},"_scale":{"__type__":"cc.Vec3","x":1,"y":1,"z":1}},{"__type__":"cc.Sprite","node":{"__id__":2},"_spriteFrame":{"__uuid__":"0auNMVHcVLPJrm9HelBe/G"}},{"__type__":"cc.Node","_name":"cube_face_0_Group","_parent":{"__id__":1},"_children":[{"__id__":5}],"_prefab":{"__type__":"cc.PrefabInfo","root":{"__id__":1},"asset":{"__uuid__":"aa/BY2+fNF8o4wSArTqmho"},"fileId":"aaMVHR9pxAr6mo0yfnTZ3h"},"_opacity":0,"_position":{"__type__":"cc.Vec3","y":-29.6},"_scale":{"__type__":"cc.Vec3","x":1.09,"y":0.89,"z":1}},{"__type__":"cc.Node","_name":"cube_face_0","_parent":{"__id__":4},"_components":[{"__id__":6}],"_prefab":{"__type__":"cc.PrefabInfo","root":{"__id__":1},"asset":{"__uuid__":"aa/BY2+fNF8o4wSArTqmho"},"fileId":"a3le3MYbtKbpy/JR46Qg3e"},"_contentSize":{"__type__":"cc.Size","width":86,"height":73},"_position":{"__type__":"cc.Vec3","y":29.6},"_scale":{"__type__":"cc.Vec3","x":1,"y":1,"z":1}},{"__type__":"cc.Sprite","node":{"__id__":5},"_spriteFrame":{"__uuid__":"0auNMVHcVLPJrm9HelBe/G"}},{"__type__":"cc.Node","_name":"cube_Group","_parent":{"__id__":1},"_children":[{"__id__":8}],"_prefab":{"__type__":"cc.PrefabInfo","root":{"__id__":1},"asset":{"__uuid__":"aa/BY2+fNF8o4wSArTqmho"},"fileId":"bbuAwvmO1Jr7HIxXj4/UAj"},"_position":{"__type__":"cc.Vec3","y":-29.6},"_scale":{"__type__":"cc.Vec3","x":1,"y":1,"z":1}},{"__type__":"cc.Node","_name":"cube","_parent":{"__id__":7},"_components":[{"__id__":9}],"_prefab":{"__type__":"cc.PrefabInfo","root":{"__id__":1},"asset":{"__uuid__":"aa/BY2+fNF8o4wSArTqmho"},"fileId":"8aO3sXiZdMsaXF0YFti5pj"},"_contentSize":{"__type__":"cc.Size","width":84,"height":73},"_position":{"__type__":"cc.Vec3","y":29.6},"_scale":{"__type__":"cc.Vec3","x":1,"y":1,"z":1}},{"__type__":"cc.Sprite","node":{"__id__":8},"_spriteFrame":{"__uuid__":"fblIFhOL9GVLEJI3YWj5JD"}},{"__type__":"cc.Node","_name":"water","_parent":{"__id__":1},"_active":false,"_components":[{"__id__":11},{"__type__":"cc.Widget","node":{"__id__":10},"alignMode":0,"_alignFlags":44,"_originalWidth":87}],"_prefab":{"__type__":"cc.PrefabInfo","root":{"__id__":1},"asset":{"__uuid__":"aa/BY2+fNF8o4wSArTqmho"},"fileId":"2dMfRFjkFH17SyJ/x3F3G1"},"_contentSize":{"__type__":"cc.Size","width":90,"height":68},"_position":{"__type__":"cc.Vec3","y":-5},"_scale":{"__type__":"cc.Vec3","x":1,"y":1,"z":1}},{"__type__":"cc.Sprite","node":{"__id__":10},"_enabled":false,"_spriteFrame":{"__uuid__":"22QiYW7BJFprfv0uXsb5b+"},"_sizeMode":0},{"__type__":"cc.Animation","node":{"__id__":1},"_clips":[{"__uuid__":"a1U0Z6dgBEPIOwBZcNJxMz"},{"__uuid__":"71MrcGFJRJD6LHM/xMvLYm"},{"__uuid__":"1469PFx2tAB47H5xbG2y6P"}]}]]