[{"__type__":"cc.SpriteFrame","content":{"name":"role_2_hand","texture":"1f0e5bb57","rect":[1953,381,90,90],"offset":[0,0],"originalSize":[90,90],"capInsets":[0,0,0,0]}},{"__type__":"cc.SpriteFrame","content":{"name":"icon_ad","texture":"1535daf7c","rect":[1067,1794,42,42],"offset":[0,0],"originalSize":[42,42],"capInsets":[0,0,0,0]}},{"__type__":"cc.SpriteFrame","content":{"name":"txt_role_try","texture":"1535daf7c","rect":[673,1945,180,53],"offset":[0,0.5],"originalSize":[180,54],"capInsets":[0,0,0,0]}},{"__type__":"cc.SpriteFrame","content":{"name":"bg_pop","texture":"17c934622","rect":[54,155,50,50],"offset":[0,0],"originalSize":[50,50],"capInsets":[25,25,25,25]}},{"__type__":"cc.SpriteFrame","content":{"name":"light","texture":"0aRgvPRptKTJzMr9w03rxE","rect":[0,0,596,468],"offset":[0,0],"originalSize":[596,468],"capInsets":[0,0,0,0]}},[{"__type__":"cc.Prefab","_name":"UIRoleTry","data":{"__id__":1}},{"__type__":"cc.Node","_name":"UIRoleTry","_children":[{"__id__":2}],"_level":1,"_components":[{"__type__":"102f8kYvilLF5QnXsP3kTHr","node":{"__id__":1},"nodeWidget":{"__id__":2},"sprBody":{"__id__":12},"sprLeftHand":{"__id__":11},"sprRightHand":{"__id__":9},"btnTry":{"__id__":15},"btnSkip":{"__id__":14},"sprBanner":{"__id__":20},"nodeNeedJumpBtn":{"__id__":13}},{"__type__":"cc.Widget","node":{"__id__":1},"alignMode":2,"_alignFlags":45}],"_prefab":{"__type__":"cc.PrefabInfo","root":{"__id__":1},"asset":{"__uuid__":"c54fPPyfpEgKiNvZYhUphx"},"fileId":"013I9LJZVKoo5MNcGlwNvq"},"_contentSize":{"__type__":"cc.Size","width":750,"height":1334},"_position":{"__type__":"cc.Vec3","x":375,"y":667}},{"__type__":"cc.Node","_name":"Widget","_parent":{"__id__":1},"_children":[{"__id__":3},{"__id__":4},{"__id__":5},{"__id__":6},{"__id__":7},{"__id__":13},{"__id__":19}],"_level":4,"_components":[{"__type__":"cc.Widget","node":{"__id__":2},"alignMode":2,"_alignFlags":45}],"_prefab":{"__type__":"cc.PrefabInfo","root":{"__id__":1},"asset":{"__uuid__":"c54fPPyfpEgKiNvZYhUphx"},"fileId":"27zDoS8I1MEICAa1XWohMD"},"_contentSize":{"__type__":"cc.Size","width":750,"height":1334}},{"__type__":"cc.Node","_name":"Mask","_parent":{"__id__":2},"_level":5,"_components":[{"__type__":"cc.Sprite","node":{"__id__":3},"_spriteFrame":{"__uuid__":"dbL15QdLhM3rz7ux6x+RuT"},"_type":1,"_sizeMode":0},{"__type__":"cc.Widget","node":{"__id__":3},"alignMode":2,"_alignFlags":45,"_originalWidth":16,"_originalHeight":16},{"__type__":"cc.BlockInputEvents","node":{"__id__":3}}],"_prefab":{"__type__":"cc.PrefabInfo","root":{"__id__":1},"asset":{"__uuid__":"c54fPPyfpEgKiNvZYhUphx"},"fileId":"f3CuOu2m9CBaUgezIDGg9k"},"_opacity":200,"_color":{"__type__":"cc.Color"},"_contentSize":{"__type__":"cc.Size","width":750,"height":1334}},{"__type__":"cc.Node","_name":"Bg","_parent":{"__id__":2},"_level":5,"_components":[{"__type__":"cc.Sprite","node":{"__id__":4},"_spriteFrame":{"__uuid__":"3f1CjnIR9AnasHWxqZNzgZ"},"_type":1,"_sizeMode":0}],"_prefab":{"__type__":"cc.PrefabInfo","root":{"__id__":1},"asset":{"__uuid__":"c54fPPyfpEgKiNvZYhUphx"},"fileId":"30+cIcf9RF/pIgD8Otw5dV"},"_contentSize":{"__type__":"cc.Size","width":596,"height":480},"_position":{"__type__":"cc.Vec3","y":193}},{"__type__":"cc.Node","_name":"Light","_parent":{"__id__":2},"_level":5,"_components":[{"__type__":"cc.Sprite","node":{"__id__":5},"_spriteFrame":{"__uuid__":"65Q5mCtChAd7qwxW9xqf7y"}}],"_prefab":{"__type__":"cc.PrefabInfo","root":{"__id__":1},"asset":{"__uuid__":"c54fPPyfpEgKiNvZYhUphx"},"fileId":"0eBBOsOy9E3IA/OKMAi77U"},"_color":{"__type__":"cc.Color","r":201,"g":161,"b":255},"_contentSize":{"__type__":"cc.Size","width":596,"height":468},"_position":{"__type__":"cc.Vec3","y":193}},{"__type__":"cc.Node","_name":"Titile","_parent":{"__id__":2},"_level":5,"_components":[{"__type__":"cc.Sprite","node":{"__id__":6},"_spriteFrame":{"__uuid__":"29NWOrWlxDIbdIvkHcON6F"}}],"_prefab":{"__type__":"cc.PrefabInfo","root":{"__id__":1},"asset":{"__uuid__":"c54fPPyfpEgKiNvZYhUphx"},"fileId":"db4Vcs2NZM8ItR+FushEwT"},"_contentSize":{"__type__":"cc.Size","width":180,"height":53},"_position":{"__type__":"cc.Vec3","y":350}},{"__type__":"cc.Node","_name":"Role","_parent":{"__id__":2},"_children":[{"__id__":8},{"__id__":10}],"_level":5,"_components":[{"__id__":12}],"_prefab":{"__type__":"cc.PrefabInfo","root":{"__id__":1},"asset":{"__uuid__":"c54fPPyfpEgKiNvZYhUphx"},"fileId":"e3rDuCNd1OUZ8u8VA4/E5e"},"_contentSize":{"__type__":"cc.Size","width":180,"height":180},"_position":{"__type__":"cc.Vec3","y":193}},{"__type__":"cc.Node","_name":"RightHand","_parent":{"__id__":7},"_level":6,"_components":[{"__id__":9}],"_prefab":{"__type__":"cc.PrefabInfo","root":{"__id__":1},"asset":{"__uuid__":"c54fPPyfpEgKiNvZYhUphx"},"fileId":"c5sFvsWoJGoIcNfKPhz0Vg"},"_contentSize":{"__type__":"cc.Size","width":90,"height":90},"_position":{"__type__":"cc.Vec3","x":-75,"y":-90}},{"__type__":"cc.Sprite","node":{"__id__":8},"_spriteFrame":{"__uuid__":"0bHLbWCRNPlarC8URs9bin"}},{"__type__":"cc.Node","_name":"LeftHand","_parent":{"__id__":7},"_level":6,"_components":[{"__id__":11}],"_prefab":{"__type__":"cc.PrefabInfo","root":{"__id__":1},"asset":{"__uuid__":"c54fPPyfpEgKiNvZYhUphx"},"fileId":"94ESOZk+JJGYjcQ17yZZL7"},"_contentSize":{"__type__":"cc.Size","width":90,"height":90},"_position":{"__type__":"cc.Vec3","x":75,"y":-90}},{"__type__":"cc.Sprite","node":{"__id__":10},"_spriteFrame":{"__uuid__":"0bHLbWCRNPlarC8URs9bin"}},{"__type__":"cc.Sprite","node":{"__id__":7},"_spriteFrame":{"__uuid__":"cajoXWn+dKwIRfuijOi1op"}},{"__type__":"cc.Node","_name":"nodeNeedJumpBtn","_parent":{"__id__":2},"_children":[{"__id__":14},{"__id__":15}],"_level":5,"_prefab":{"__type__":"cc.PrefabInfo","root":{"__id__":1},"asset":{"__uuid__":"c54fPPyfpEgKiNvZYhUphx"},"fileId":"90pu56qptAxbNlO7qRNX+Y"},"_contentSize":{"__type__":"cc.Size","width":315,"height":230},"_position":{"__type__":"cc.Vec3","x":1,"y":-285}},{"__type__":"cc.Node","_name":"BtnSkip","_parent":{"__id__":13},"_level":6,"_components":[{"__type__":"cc.Sprite","node":{"__id__":14},"_spriteFrame":{"__uuid__":"cezmbihLNCx4n8rohMkQgd"}},{"__type__":"cc.Button","node":{"__id__":14},"zoomScale":0.8,"_N$transition":3,"transition":3}],"_prefab":{"__type__":"cc.PrefabInfo","root":{"__id__":1},"asset":{"__uuid__":"c54fPPyfpEgKiNvZYhUphx"},"fileId":"4er2V50n1ClLrETJDWBKL2"},"_contentSize":{"__type__":"cc.Size","width":160,"height":40},"_position":{"__type__":"cc.Vec3","x":-1,"y":-88}},{"__type__":"cc.Node","_name":"BtnBig","_parent":{"__id__":13},"_children":[{"__id__":16},{"__id__":17},{"__id__":18}],"_level":6,"_components":[{"__type__":"cc.Sprite","node":{"__id__":15},"_spriteFrame":{"__uuid__":"ecC+3v1DVHaaX2jWjbseoE"},"_type":1},{"__type__":"cc.Button","node":{"__id__":15},"zoomScale":0.8,"_N$transition":3,"transition":3}],"_prefab":{"__type__":"cc.PrefabInfo","root":{"__id__":1},"asset":{"__uuid__":"c54fPPyfpEgKiNvZYhUphx"},"fileId":"a2xyj/5+BFBL5fcF0IkyEP"},"_color":{"__type__":"cc.Color","r":178,"g":255,"b":114},"_contentSize":{"__type__":"cc.Size","width":304,"height":98},"_position":{"__type__":"cc.Vec3","x":-1,"y":63}},{"__type__":"cc.Node","_name":"BtnBig","_parent":{"__id__":15},"_level":6,"_components":[{"__type__":"cc.Sprite","node":{"__id__":16},"_spriteFrame":{"__uuid__":"ecC+3v1DVHaaX2jWjbseoE"}}],"_prefab":{"__type__":"cc.PrefabInfo","root":{"__id__":1},"asset":{"__uuid__":"c54fPPyfpEgKiNvZYhUphx"},"fileId":"a6DSQfublKH5bQ9odmj/1G"},"_color":{"__type__":"cc.Color","r":94,"g":203,"b":74},"_contentSize":{"__type__":"cc.Size","width":304,"height":98},"_scale":{"__type__":"cc.Vec3","x":0.95,"y":0.85,"z":1}},{"__type__":"cc.Node","_name":"txt_start","_parent":{"__id__":15},"_level":6,"_components":[{"__type__":"cc.Sprite","node":{"__id__":17},"_spriteFrame":{"__uuid__":"dcwP0zPAJH/5GI7qkAvAPX"}}],"_prefab":{"__type__":"cc.PrefabInfo","root":{"__id__":1},"asset":{"__uuid__":"c54fPPyfpEgKiNvZYhUphx"},"fileId":"85TDKxdSxDBJCXgLtXRhQF"},"_contentSize":{"__type__":"cc.Size","width":165,"height":48},"_position":{"__type__":"cc.Vec3","x":18.3}},{"__type__":"cc.Node","_name":"ad","_parent":{"__id__":15},"_level":6,"_components":[{"__type__":"cc.Sprite","node":{"__id__":18},"_spriteFrame":{"__uuid__":"0bZpEBxARMW41B5c+Aa+jB"}}],"_prefab":{"__type__":"cc.PrefabInfo","root":{"__id__":1},"asset":{"__uuid__":"c54fPPyfpEgKiNvZYhUphx"},"fileId":"79RC3kvARLq4ZSWLWrchly"},"_contentSize":{"__type__":"cc.Size","width":42,"height":42},"_position":{"__type__":"cc.Vec3","x":-90}},{"__type__":"cc.Node","_name":"Banner","_parent":{"__id__":2},"_level":5,"_components":[{"__id__":20},{"__type__":"cc.Widget","node":{"__id__":19},"alignMode":2,"_alignFlags":44,"_originalWidth":750}],"_prefab":{"__type__":"cc.PrefabInfo","root":{"__id__":1},"asset":{"__uuid__":"c54fPPyfpEgKiNvZYhUphx"},"fileId":"1epZM+VLFB5prdC364v1TT"},"_contentSize":{"__type__":"cc.Size","width":750,"height":260},"_position":{"__type__":"cc.Vec3","y":-537}},{"__type__":"cc.Sprite","node":{"__id__":19},"_sizeMode":0}],{"__type__":"cc.SpriteFrame","content":{"name":"role_2_body","texture":"1f0e5bb57","rect":[189,757,180,180],"offset":[0,0],"originalSize":[180,180],"capInsets":[0,0,0,0]}},{"__type__":"cc.SpriteFrame","content":{"name":"txt_skip","texture":"1535daf7c","rect":[677,1673,160,40],"offset":[0,0],"originalSize":[160,40],"capInsets":[0,0,0,0]}},{"__type__":"cc.SpriteFrame","content":{"name":"imgWhite","texture":"1535daf7c","rect":[602,477,16,16],"offset":[0,0],"originalSize":[16,16],"capInsets":[2,2,2,2]}},{"__type__":"cc.SpriteFrame","content":{"name":"txt_free_try","texture":"1535daf7c","rect":[761,1051,165,48],"offset":[0.5,0],"originalSize":[166,50],"capInsets":[0,0,0,0]}},{"__type__":"cc.SpriteFrame","content":{"name":"btn_big","texture":"1535daf7c","rect":[500,775,304,98],"offset":[0,0],"originalSize":[304,100],"rotated":1,"capInsets":[0,0,0,0]}}]